{"odt":"REBRANDINGMASTERCARD8233752","userid":"522","latitud":"19.3812064","longitud":"-99.1713899","afiliacion":"8233752","comentarios":"NO SE REALIZA EL SERVICIO DEBIDO A QUE NO HAY NINGUNA PERSONA QUE PUEDA ATENDER EST\u00c1 CERRADO Y EL TEL\u00c9FONO DE CONTACTO EST\u00c1 FUERA DE SERVICIO","cve_banco":"3","tvpentrada":"No Legible","tvpsalida":"","simentrada":"","simsalida":"","atendio":"","rollosentrega":"0","rollosinstalar":"0","horaentrada":"14:9:29","horasalida":"14:12:44","horaticket":"14:07","foliotelecarga":"","idcaja":""}