{"odt":"REBRANDINGMASTERCARD7452826","userid":"522","latitud":"19.4126946","longitud":"-99.1681163","afiliacion":"7452826","comentarios":"NO SE REALIZA SERVICIO NEGOCIO CERRADO POSIBLE CAMBIO DE DIRECCI\u00d3N SE DESCONOCE PARADERO DEL DUE\u00d1O Y DEL NEGOCIO","cve_banco":"3","tvpentrada":"No Legible","tvpsalida":"","simentrada":"","simsalida":"","atendio":"","rollosentrega":"0","rollosinstalar":"0","horaentrada":"12:14:57","horasalida":"12:17:12","horaticket":"12:14","foliotelecarga":"","idcaja":""}