{"odt":"REBRANDINGMASTERCARD7514977","userid":"473","latitud":"19.3847181","longitud":"-99.1533884","afiliacion":"7514977","comentarios":"RECHAZO COMENTA MAGALLI LOZANO QUE YA NO OCUPAN LA TERMINAL DE SANTANDER LO CHECARA CON EL EJECUTIVO DE CUENTA ","cve_banco":"3","tvpentrada":"No Legible","tvpsalida":"","simentrada":"","simsalida":"","atendio":"MAGALLI LOZANO ","rollosentrega":"0","rollosinstalar":"0","horaentrada":"15:9:56","horasalida":"15:13:0","horaticket":"1510","foliotelecarga":"","idcaja":""}