{"odt":"REBRANDINGMASTERCARD7014204","userid":"520","latitud":"19.4049819","longitud":"-99.1732877","afiliacion":"7014204","comentarios":"NO SE REALIZA EL SERVICIO DEBIDO A QUE SE ACUDE EN TRES HORARIOS Y DOS D\u00cdAS DIFERENTES Y EL CONSULTORIO SE ENCUENTRA CERRADO. SE LLAMA A LOS TEL\u00c9FONOS REGISTRADOS SIN RESPUESTA. LOS VECINOS DESCONOCEN RAZ\u00d3N DEL NEGOCIO.","cve_banco":"3","tvpentrada":"No Legible","tvpsalida":"","simentrada":"","simsalida":"","atendio":"","rollosentrega":"0","rollosinstalar":"0","horaentrada":"11:34:57","horasalida":"11:37:49","horaticket":"11:25 AM","foliotelecarga":"","idcaja":""}